zdb/__init__.py
zdb/utils.py
zdb/commons/__init__.py
zdb/mysql/__init__.py
zdb/mysql/cluster.py
zdb/mysql/pool.py
zdb/oracle/__init__.py
zdb/postgresql/__init__.py
zpy_db_core-2.3.0.dist-info/licenses/LICENSE
zpy_db_core-2.3.0.dist-info/METADATA
zpy_db_core-2.3.0.dist-info/WHEEL
zpy_db_core-2.3.0.dist-info/top_level.txt
zpy_db_core-2.3.0.dist-info/RECORD
