Metadata-Version: 2.4
Name: zpy-db-core
Version: 2.3.0
Summary: Helper module for manage database connection
Home-page: https://github.com/NoeCruzMW
Author: Noé Cruz | linkedin.com/in/zurckz/
Author-email: zurckz.services@gmail.com
Classifier: Programming Language :: Python :: 3
Classifier: Programming Language :: Python :: 3.8
Classifier: Programming Language :: Python :: 3.9
Classifier: Programming Language :: Python :: 3.10
Classifier: Programming Language :: Python :: 3.11
Classifier: Programming Language :: Python :: 3.12
Classifier: Programming Language :: Python :: 3.13
Classifier: License :: OSI Approved :: MIT License
Classifier: Operating System :: OS Independent
Requires-Python: >=3.8
License-File: LICENSE
Requires-Dist: zpy-api-core>=2.3.0
Requires-Dist: mysql-connector-python
Requires-Dist: cx-Oracle
Requires-Dist: psycopg2
Dynamic: author
Dynamic: author-email
Dynamic: classifier
Dynamic: description
Dynamic: description-content-type
Dynamic: home-page
Dynamic: license-file
Dynamic: requires-dist
Dynamic: requires-python
Dynamic: summary
